setup.py
autism/__init__.py
autism/dict_proxy.py
autism/tools.py
autism/wsgi.py
autism.egg-info/PKG-INFO
autism.egg-info/SOURCES.txt
autism.egg-info/dependency_links.txt
autism.egg-info/top_level.txt