Metadata-Version: 1.1
Name: autism
Version: 0.1
Summary: Collection of useful code
Home-page: https://github.com/fritz0705/autism
Author: Fritz Grimpen
Author-email: fritz@grimpen.net
License: GNU GPLv2
Platform: UNKNOWN
Classifier: Development Status :: 4 - Beta
Classifier: Operating System :: POSIX
Classifier: Programming Language :: Python :: 3.3
Classifier: Topic :: Internet :: WWW/HTTP :: WSGI :: Application
